<?xml version="1.0" encoding="utf-8"?><rootnode>
 <Meta>
  <Source>WeChat</Source>
  <Popu>3</Popu>
  <Lang>Chinese</Lang>
  <State>D</State>
  <Gender>Unknow</Gender>
  <Note>Nothing</Note>
 </Meta>
 <Dialogue>
  <WeChat>
   <Time>2021-11-01 09:26:00</Time>
   <Sender>A</Sender>
   <Content>有啥键盘推荐不，友友们</Content>
  </WeChat>
 </Dialogue>
 <Dialogue>
  <WeChat>
   <Time>2021-11-01 09:26:00</Time>
   <Sender>A</Sender>
   <Content>[表情]</Content>
  </WeChat>
 </Dialogue>
 <Dialogue>
  <WeChat>
   <Time>2021-11-01 13:18:00</Time>
   <Sender>B</Sender>
   <Content>[图片]</Content>
  </WeChat>
 </Dialogue>
 <Dialogue>
  <WeChat>
   <Time>2021-11-01 13:19:00</Time>
   <Sender>B</Sender>
   <Content>我买了这个</Content>
  </WeChat>
 </Dialogue>
 <Dialogue>
  <WeChat>
   <Time>2021-11-01 13:19:00</Time>
   <Sender>B</Sender>
   <Content>贴吧老推荐的</Content>
  </WeChat>
 </Dialogue>
 <Dialogue>
  <WeChat>
   <Time>2021-11-01 13:19:00</Time>
   <Sender>A</Sender>
   <Content>[表情]</Content>
  </WeChat>
 </Dialogue>
 <Dialogue>
  <WeChat>
   <Time>2021-11-01 13:19:00</Time>
   <Sender>B</Sender>
   <Content>打游戏的话雷[sensitive]fl黑峡谷都行</Content>
  </WeChat>
 </Dialogue>
 <Dialogue>
  <WeChat>
   <Time>2021-11-01 13:19:00</Time>
   <Sender>A</Sender>
   <Content>有钱人</Content>
  </WeChat>
 </Dialogue>
 <Dialogue>
  <WeChat>
   <Time>2021-11-01 13:20:00</Time>
   <Sender>B</Sender>
   <Content>[表情]</Content>
  </WeChat>
 </Dialogue>
 <Dialogue>
  <WeChat>
   <Time>2021-11-01 13:20:00</Time>
   <Sender>B</Sender>
   <Content>其实你出邮费</Content>
  </WeChat>
 </Dialogue>
 <Dialogue>
  <WeChat>
   <Time>2021-11-01 13:20:00</Time>
   <Sender>B</Sender>
   <Content>我可以把我用的寄给你</Content>
  </WeChat>
 </Dialogue>
 <Dialogue>
  <WeChat>
   <Time>2021-11-01 13:20:00</Time>
   <Sender>A</Sender>
   <Content>[表情]</Content>
  </WeChat>
 </Dialogue>
 <Dialogue>
  <WeChat>
   <Time>2021-11-01 13:20:00</Time>
   <Sender>B</Sender>
   <Content>我之前买了一个入门级的</Content>
  </WeChat>
 </Dialogue>
 <Dialogue>
  <WeChat>
   <Time>2021-11-01 13:20:00</Time>
   <Sender>B</Sender>
   <Content>黑峡谷</Content>
  </WeChat>
 </Dialogue>
 <Dialogue>
  <WeChat>
   <Time>2021-11-01 13:20:00</Time>
   <Sender>B</Sender>
   <Content>200左右</Content>
  </WeChat>
 </Dialogue>
 <Dialogue>
  <WeChat>
   <Time>2021-11-01 13:20:00</Time>
   <Sender>A</Sender>
   <Content>好活</Content>
  </WeChat>
 </Dialogue>
 <Dialogue>
  <WeChat>
   <Time>2021-11-01 13:20:00</Time>
   <Sender>A</Sender>
   <Content>[表情]</Content>
  </WeChat>
 </Dialogue>
 <Dialogue>
  <WeChat>
   <Time>2021-11-01 13:20:00</Time>
   <Sender>B</Sender>
   <Content>但是u键坏了</Content>
  </WeChat>
 </Dialogue>
 <Dialogue>
  <WeChat>
   <Time>2021-11-01 13:21:00</Time>
   <Sender>B</Sender>
   <Content>而且键盘很脏</Content>
  </WeChat>
 </Dialogue>
 <Dialogue>
  <WeChat>
   <Time>2021-11-01 13:21:00</Time>
   <Sender>B</Sender>
   <Content>可拆卸</Content>
  </WeChat>
 </Dialogue>
 <Dialogue>
  <WeChat>
   <Time>2021-11-01 13:21:00</Time>
   <Sender>A</Sender>
   <Content>拆了修一下就好</Content>
  </WeChat>
 </Dialogue>
 <Dialogue>
  <WeChat>
   <Time>2021-11-01 13:21:00</Time>
   <Sender>A</Sender>
   <Content>[表情]</Content>
  </WeChat>
 </Dialogue>
 <Dialogue>
  <WeChat>
   <Time>2021-11-01 13:21:00</Time>
   <Sender>A</Sender>
   <Content>[图片]</Content>
  </WeChat>
 </Dialogue>
 <Dialogue>
  <WeChat>
   <Time>2021-11-01 13:21:00</Time>
   <Sender>A</Sender>
   <Content>看到我的电烙铁没</Content>
  </WeChat>
 </Dialogue>
 <Dialogue>
  <WeChat>
   <Time>2021-11-01 13:21:00</Time>
   <Sender>A</Sender>
   <Content>[表情]</Content>
  </WeChat>
 </Dialogue>
 <Dialogue>
  <WeChat>
   <Time>2021-11-01 13:22:00</Time>
   <Sender>B</Sender>
   <Content>[图片]</Content>
  </WeChat>
 </Dialogue>
 <Dialogue>
  <WeChat>
   <Time>2021-11-01 13:22:00</Time>
   <Sender>B</Sender>
   <Content>我之前做实验用了那玩意</Content>
  </WeChat>
 </Dialogue>
 <Dialogue>
  <WeChat>
   <Time>2021-11-01 13:22:00</Time>
   <Sender>B</Sender>
   <Content>你自己买的？</Content>
  </WeChat>
 </Dialogue>
 <Dialogue>
  <WeChat>
   <Time>2021-11-01 13:22:00</Time>
   <Sender>B</Sender>
   <Content>你出邮费</Content>
  </WeChat>
 </Dialogue>
 <Dialogue>
  <WeChat>
   <Time>2021-11-01 13:22:00</Time>
   <Sender>A</Sender>
   <Content>嗯</Content>
  </WeChat>
 </Dialogue>
 <Dialogue>
  <WeChat>
   <Time>2021-11-01 13:22:00</Time>
   <Sender>B</Sender>
   <Content>我哪天给你寄过来</Content>
  </WeChat>
 </Dialogue>
 <Dialogue>
  <WeChat>
   <Time>2021-11-01 13:22:00</Time>
   <Sender>A</Sender>
   <Content>先不急</Content>
  </WeChat>
 </Dialogue>
 <Dialogue>
  <WeChat>
   <Time>2021-11-01 13:22:00</Time>
   <Sender>B</Sender>
   <Content>等我键盘到了</Content>
  </WeChat>
 </Dialogue>
 <Dialogue>
  <WeChat>
   <Time>2021-11-01 13:22:00</Time>
   <Sender>B</Sender>
   <Content>[表情]</Content>
  </WeChat>
 </Dialogue>
 <Dialogue>
  <WeChat>
   <Time>2021-11-01 13:23:00</Time>
   <Sender>A</Sender>
   <Content>这段[sensitive]兰州快递不行</Content>
  </WeChat>
 </Dialogue>
 <Dialogue>
  <WeChat>
   <Time>2021-11-01 13:23:00</Time>
   <Sender>B</Sender>
   <Content>我还正愁这把键盘放哪里</Content>
  </WeChat>
 </Dialogue>
 <Dialogue>
  <WeChat>
   <Time>2021-11-01 13:23:00</Time>
   <Sender>B</Sender>
   <Content>打算吃灰的</Content>
  </WeChat>
 </Dialogue>
 <Dialogue>
  <WeChat>
   <Time>2021-11-01 13:23:00</Time>
   <Sender>B</Sender>
   <Content>[表情]</Content>
  </WeChat>
 </Dialogue>
 <Dialogue>
  <WeChat>
   <Time>2021-11-01 13:23:00</Time>
   <Sender>B</Sender>
   <Content>键帽你可以自己换</Content>
  </WeChat>
 </Dialogue>
 <Dialogue>
  <WeChat>
   <Time>2021-11-01 13:23:00</Time>
   <Sender>B</Sender>
   <Content>键帽不太好</Content>
  </WeChat>
 </Dialogue>
 <Dialogue>
  <WeChat>
   <Time>2021-11-01 13:23:00</Time>
   <Sender>A</Sender>
   <Content>正愁着没钱</Content>
  </WeChat>
 </Dialogue>
 <Dialogue>
  <WeChat>
   <Time>2021-11-01 13:23:00</Time>
   <Sender>B</Sender>
   <Content>轴很香</Content>
  </WeChat>
 </Dialogue>
 <Dialogue>
  <WeChat>
   <Time>2021-11-01 13:24:00</Time>
   <Sender>A</Sender>
   <Content>[表情]</Content>
  </WeChat>
 </Dialogue>
 <Dialogue>
  <WeChat>
   <Time>2021-11-01 13:24:00</Time>
   <Sender>B</Sender>
   <Content>凯华box轴</Content>
  </WeChat>
 </Dialogue>
 <Dialogue>
  <WeChat>
   <Time>2021-11-01 13:24:00</Time>
   <Sender>B</Sender>
   <Content>入门级天花板</Content>
  </WeChat>
 </Dialogue>
 <Dialogue>
  <WeChat>
   <Time>2021-11-01 13:24:00</Time>
   <Sender>B</Sender>
   <Content>我去年看了贼久</Content>
  </WeChat>
 </Dialogue>
 <Dialogue>
  <WeChat>
   <Time>2021-11-01 13:24:00</Time>
   <Sender>B</Sender>
   <Content>然后又穷</Content>
  </WeChat>
 </Dialogue>
 <Dialogue>
  <WeChat>
   <Time>2021-11-01 13:24:00</Time>
   <Sender>A</Sender>
   <Content>为什么你们这么有钱</Content>
  </WeChat>
 </Dialogue>
 <Dialogue>
  <WeChat>
   <Time>2021-11-01 13:25:00</Time>
   <Sender>A</Sender>
   <Content>[表情]</Content>
  </WeChat>
 </Dialogue>
 <Dialogue>
  <WeChat>
   <Time>2021-11-01 13:25:00</Time>
   <Sender>A</Sender>
   <Content>我现在欠债无数</Content>
  </WeChat>
 </Dialogue>
 <Dialogue>
  <WeChat>
   <Time>2021-11-01 13:25:00</Time>
   <Sender>A</Sender>
   <Content>只能勉强维持生活</Content>
  </WeChat>
 </Dialogue>
 <Dialogue>
  <WeChat>
   <Time>2021-11-01 13:25:00</Time>
   <Sender>A</Sender>
   <Content>[表情]</Content>
  </WeChat>
 </Dialogue>
 <Dialogue>
  <WeChat>
   <Time>2021-11-01 13:25:00</Time>
   <Sender>A</Sender>
   <Content>昨天还把手机屏幕摔碎了</Content>
  </WeChat>
 </Dialogue>
 <Dialogue>
  <WeChat>
   <Time>2021-11-01 13:26:00</Time>
   <Sender>B</Sender>
   <Content>有个屁钱</Content>
  </WeChat>
 </Dialogue>
 <Dialogue>
  <WeChat>
   <Time>2021-11-01 13:26:00</Time>
   <Sender>B</Sender>
   <Content>[表情]</Content>
  </WeChat>
 </Dialogue>
 <Dialogue>
  <WeChat>
   <Time>2021-11-01 13:26:00</Time>
   <Sender>B</Sender>
   <Content>都是自己存的</Content>
  </WeChat>
 </Dialogue>
 <Dialogue>
  <WeChat>
   <Time>2021-11-01 13:27:00</Time>
   <Sender>B</Sender>
   <Content>还有父母多给的</Content>
  </WeChat>
 </Dialogue>
 <Dialogue>
  <WeChat>
   <Time>2021-11-01 13:27:00</Time>
   <Sender>A</Sender>
   <Content>[流泪]</Content>
  </WeChat>
 </Dialogue>
 <Dialogue>
  <WeChat>
   <Time>2021-11-01 13:27:00</Time>
   <Sender>A</Sender>
   <Content>我现在存的钱一毛没了</Content>
  </WeChat>
 </Dialogue>
 <Dialogue>
  <WeChat>
   <Time>2021-11-01 13:27:00</Time>
   <Sender>A</Sender>
   <Content>还欠债</Content>
  </WeChat>
 </Dialogue>
 <Dialogue>
  <WeChat>
   <Time>2021-11-01 13:28:00</Time>
   <Sender>B</Sender>
   <Content>你又没女朋友</Content>
  </WeChat>
 </Dialogue>
 <Dialogue>
  <WeChat>
   <Time>2021-11-01 13:28:00</Time>
   <Sender>A</Sender>
   <Content>买了电脑</Content>
  </WeChat>
 </Dialogue>
 <Dialogue>
  <WeChat>
   <Time>2021-11-01 13:28:00</Time>
   <Sender>B</Sender>
   <Content>哪有那么多花钱的地方</Content>
  </WeChat>
 </Dialogue>
 <Dialogue>
  <WeChat>
   <Time>2021-11-01 13:28:00</Time>
   <Sender>A</Sender>
   <Content>[害羞]</Content>
  </WeChat>
 </Dialogue>
 <Dialogue>
  <WeChat>
   <Time>2021-11-01 13:28:00</Time>
   <Sender>C</Sender>
   <Content>[表情]</Content>
  </WeChat>
 </Dialogue>
 <Dialogue>
  <WeChat>
   <Time>2021-11-01 13:28:00</Time>
   <Sender>B</Sender>
   <Content>[表情]</Content>
  </WeChat>
 </Dialogue>
 <Dialogue>
  <WeChat>
   <Time>2021-11-01 13:28:00</Time>
   <Sender>B</Sender>
   <Content>9000多电脑</Content>
  </WeChat>
 </Dialogue>
 <Dialogue>
  <WeChat>
   <Time>2021-11-01 13:28:00</Time>
   <Sender>C</Sender>
   <Content>没钱找我借</Content>
  </WeChat>
 </Dialogue>
 <Dialogue>
  <WeChat>
   <Time>2021-11-01 13:28:00</Time>
   <Sender>B</Sender>
   <Content>跟我说没钱</Content>
  </WeChat>
 </Dialogue>
 <Dialogue>
  <WeChat>
   <Time>2021-11-01 13:28:00</Time>
   <Sender>C</Sender>
   <Content>利息不贵</Content>
  </WeChat>
 </Dialogue>
 <Dialogue>
  <WeChat>
   <Time>2021-11-01 13:28:00</Time>
   <Sender>B</Sender>
   <Content>[sensitive]</Content>
  </WeChat>
 </Dialogue>
 <Dialogue>
  <WeChat>
   <Time>2021-11-01 13:28:00</Time>
   <Sender>B</Sender>
   <Content>[表情]</Content>
  </WeChat>
 </Dialogue>
 <Dialogue>
  <WeChat>
   <Time>2021-11-01 13:28:00</Time>
   <Sender>A</Sender>
   <Content>哈哈哈</Content>
  </WeChat>
 </Dialogue>
 <Dialogue>
  <WeChat>
   <Time>2021-11-01 13:28:00</Time>
   <Sender>A</Sender>
   <Content>可以可以</Content>
  </WeChat>
 </Dialogue>
 <Dialogue>
  <WeChat>
   <Time>2021-11-01 13:28:00</Time>
   <Sender>C</Sender>
   <Content>也就20块钱收五块吧</Content>
  </WeChat>
 </Dialogue>
 <Dialogue>
  <WeChat>
   <Time>2021-11-01 13:29:00</Time>
   <Sender>A</Sender>
   <Content>我群第一富[sensitive]</Content>
  </WeChat>
 </Dialogue>
 <Dialogue>
  <WeChat>
   <Time>2021-11-01 13:29:00</Time>
   <Sender>A</Sender>
   <Content>。。。。。</Content>
  </WeChat>
 </Dialogue>
 <Dialogue>
  <WeChat>
   <Time>2021-11-01 13:29:00</Time>
   <Sender>B</Sender>
   <Content>[表情]</Content>
  </WeChat>
 </Dialogue>
 <Dialogue>
  <WeChat>
   <Time>2021-11-01 13:29:00</Time>
   <Sender>A</Sender>
   <Content>[表情]</Content>
  </WeChat>
 </Dialogue>
 <Dialogue>
  <WeChat>
   <Time>2021-11-01 13:29:00</Time>
   <Sender>A</Sender>
   <Content>[sensitive]都没你利高</Content>
  </WeChat>
 </Dialogue>
 <Dialogue>
  <WeChat>
   <Time>2021-11-01 13:29:00</Time>
   <Sender>B</Sender>
   <Content>[表情]</Content>
  </WeChat>
 </Dialogue>
 <Dialogue>
  <WeChat>
   <Time>2021-11-01 13:29:00</Time>
   <Sender>B</Sender>
   <Content>确实</Content>
  </WeChat>
 </Dialogue>
 <Dialogue>
  <WeChat>
   <Time>2021-11-01 13:30:00</Time>
   <Sender>C</Sender>
   <Content>[表情]</Content>
  </WeChat>
 </Dialogue>
 <Dialogue>
  <WeChat>
   <Time>2021-11-01 13:30:00</Time>
   <Sender>C</Sender>
   <Content>以后找我借钱 还的时候给杯奶茶钱就好</Content>
  </WeChat>
 </Dialogue>
 <Dialogue>
  <WeChat>
   <Time>2021-11-01 13:30:00</Time>
   <Sender>A</Sender>
   <Content>[表情]</Content>
  </WeChat>
 </Dialogue>
 <Dialogue>
  <WeChat>
   <Time>2021-11-01 13:30:00</Time>
   <Sender>C</Sender>
   <Content>（哈哈哈哈哈哈）虽然你们也用不着 发自我的 iPhone</Content>
  </WeChat>
 </Dialogue>
</rootnode>