<?xml version="1.0" encoding="utf-8"?><rootnode>
 <Meta>
  <Source>WeChat</Source>
  <Popu>2</Popu>
  <Lang>Chinese</Lang>
  <State>D</State>
  <Gender>Unknow</Gender>
  <Note>Nothing</Note>
 </Meta>
 <Dialogue>
  <WeChat>
   <Time>2022-07-13 21:13:00</Time>
   <Sender>A</Sender>
   <Content>所以我还是不知道我明天面试的时间和序号啥的</Content>
  </WeChat>
 </Dialogue>
 <Dialogue>
  <WeChat>
   <Time>2022-07-13 21:14:00</Time>
   <Sender>B</Sender>
   <Content>？</Content>
  </WeChat>
 </Dialogue>
 <Dialogue>
  <WeChat>
   <Time>2022-07-13 21:14:00</Time>
   <Sender>B</Sender>
   <Content>那应该不至于</Content>
  </WeChat>
 </Dialogue>
 <Dialogue>
  <WeChat>
   <Time>2022-07-13 21:14:00</Time>
   <Sender>B</Sender>
   <Content>我们组已经规划好了次序</Content>
  </WeChat>
 </Dialogue>
 <Dialogue>
  <WeChat>
   <Time>2022-07-13 21:14:00</Time>
   <Sender>A</Sender>
   <Content>在哪看啊[尴尬]</Content>
  </WeChat>
 </Dialogue>
 <Dialogue>
  <WeChat>
   <Time>2022-07-13 21:14:00</Time>
   <Sender>A</Sender>
   <Content>不是</Content>
  </WeChat>
 </Dialogue>
 <Dialogue>
  <WeChat>
   <Time>2022-07-13 21:14:00</Time>
   <Sender>A</Sender>
   <Content>张[sensitive]刚拉我进群</Content>
  </WeChat>
 </Dialogue>
 <Dialogue>
  <WeChat>
   <Time>2022-07-13 21:14:00</Time>
   <Sender>B</Sender>
   <Content>你们组负责人会发吧</Content>
  </WeChat>
 </Dialogue>
 <Dialogue>
  <WeChat>
   <Time>2022-07-13 21:14:00</Time>
   <Sender>A</Sender>
   <Content>群里啥也没有</Content>
  </WeChat>
 </Dialogue>
 <Dialogue>
  <WeChat>
   <Time>2022-07-13 21:15:00</Time>
   <Sender>A</Sender>
   <Content>他们都改好了序号</Content>
  </WeChat>
 </Dialogue>
 <Dialogue>
  <WeChat>
   <Time>2022-07-13 21:15:00</Time>
   <Sender>B</Sender>
   <Content>你要不问问群里认识的</Content>
  </WeChat>
 </Dialogue>
 <Dialogue>
  <WeChat>
   <Time>2022-07-13 21:15:00</Time>
   <Sender>A</Sender>
   <Content>ok</Content>
  </WeChat>
 </Dialogue>
 <Dialogue>
  <WeChat>
   <Time>2022-07-13 21:15:00</Time>
   <Sender>B</Sender>
   <Content>估计你进晚了</Content>
  </WeChat>
 </Dialogue>
 <Dialogue>
  <WeChat>
   <Time>2022-07-13 21:15:00</Time>
   <Sender>A</Sender>
   <Content>不是估计</Content>
  </WeChat>
 </Dialogue>
 <Dialogue>
  <WeChat>
   <Time>2022-07-13 21:15:00</Time>
   <Sender>A</Sender>
   <Content>是就是把我忘了</Content>
  </WeChat>
 </Dialogue>
 <Dialogue>
  <WeChat>
   <Time>2022-07-13 21:15:00</Time>
   <Sender>B</Sender>
   <Content>哈哈哈哈</Content>
  </WeChat>
 </Dialogue>
</rootnode>