<?xml version="1.0" encoding="utf-8"?><rootnode>
 <Meta>
  <Source>WeChat</Source>
  <Popu>2</Popu>
  <Lang>Chinese</Lang>
  <State>D</State>
  <Gender>Unknow</Gender>
  <Note>Nothing</Note>
 </Meta>
 <Dialogue>
  <WeChat>
   <Time>2022-09-26 15:20:00</Time>
   <Sender>A</Sender>
   <Content>邓[sensitive]老师</Content>
  </WeChat>
 </Dialogue>
 <Dialogue>
  <WeChat>
   <Time>2022-09-26 15:22:00</Time>
   <Sender>B</Sender>
   <Content>咋</Content>
  </WeChat>
 </Dialogue>
 <Dialogue>
  <WeChat>
   <Time>2022-09-26 15:23:00</Time>
   <Sender>A</Sender>
   <Content>你们国庆放几天假？</Content>
  </WeChat>
 </Dialogue>
 <Dialogue>
  <WeChat>
   <Time>2022-09-26 15:23:00</Time>
   <Sender>B</Sender>
   <Content>3天</Content>
  </WeChat>
 </Dialogue>
 <Dialogue>
  <WeChat>
   <Time>2022-09-26 15:23:00</Time>
   <Sender>A</Sender>
   <Content>和姚[sensitive]他们一样</Content>
  </WeChat>
 </Dialogue>
 <Dialogue>
  <WeChat>
   <Time>2022-09-26 15:24:00</Time>
   <Sender>A</Sender>
   <Content>终于快读书了</Content>
  </WeChat>
 </Dialogue>
 <Dialogue>
  <WeChat>
   <Time>2022-09-26 15:24:00</Time>
   <Sender>A</Sender>
   <Content>这次又不想去武汉</Content>
  </WeChat>
 </Dialogue>
 <Dialogue>
  <WeChat>
   <Time>2022-09-26 15:24:00</Time>
   <Sender>B</Sender>
   <Content>666</Content>
  </WeChat>
 </Dialogue>
 <Dialogue>
  <WeChat>
   <Time>2022-09-26 15:24:00</Time>
   <Sender>A</Sender>
   <Content>变成一个人了</Content>
  </WeChat>
 </Dialogue>
 <Dialogue>
  <WeChat>
   <Time>2022-09-26 15:24:00</Time>
   <Sender>A</Sender>
   <Content>唉</Content>
  </WeChat>
 </Dialogue>
 <Dialogue>
  <WeChat>
   <Time>2022-09-26 15:24:00</Time>
   <Sender>A</Sender>
   <Content>害怕回到武汉</Content>
  </WeChat>
 </Dialogue>
 <Dialogue>
  <WeChat>
   <Time>2022-09-26 15:24:00</Time>
   <Sender>A</Sender>
   <Content>你懂不</Content>
  </WeChat>
 </Dialogue>
 <Dialogue>
  <WeChat>
   <Time>2022-09-26 15:24:00</Time>
   <Sender>A</Sender>
   <Content>那种感觉</Content>
  </WeChat>
 </Dialogue>
 <Dialogue>
  <WeChat>
   <Time>2022-09-26 15:24:00</Time>
   <Sender>B</Sender>
   <Content>哈哈哈哈哈</Content>
  </WeChat>
 </Dialogue>
 <Dialogue>
  <WeChat>
   <Time>2022-09-26 15:25:00</Time>
   <Sender>A</Sender>
   <Content>妈的</Content>
  </WeChat>
 </Dialogue>
 <Dialogue>
  <WeChat>
   <Time>2022-09-26 15:25:00</Time>
   <Sender>A</Sender>
   <Content>早知道在长沙挺好的</Content>
  </WeChat>
 </Dialogue>
 <Dialogue>
  <WeChat>
   <Time>2022-09-26 15:25:00</Time>
   <Sender>B</Sender>
   <Content>[旺柴]</Content>
  </WeChat>
 </Dialogue>
 <Dialogue>
  <WeChat>
   <Time>2022-09-26 15:25:00</Time>
   <Sender>A</Sender>
   <Content>都不敢去了</Content>
  </WeChat>
 </Dialogue>
 <Dialogue>
  <WeChat>
   <Time>2022-09-26 15:25:00</Time>
   <Sender>A</Sender>
   <Content>他那时候</Content>
  </WeChat>
 </Dialogue>
 <Dialogue>
  <WeChat>
   <Time>2022-09-26 15:25:00</Time>
   <Sender>A</Sender>
   <Content>给你来一句</Content>
  </WeChat>
 </Dialogue>
 <Dialogue>
  <WeChat>
   <Time>2022-09-26 15:26:00</Time>
   <Sender>A</Sender>
   <Content>你在武汉还不如在长沙</Content>
  </WeChat>
 </Dialogue>
 <Dialogue>
  <WeChat>
   <Time>2022-09-26 15:26:00</Time>
   <Sender>A</Sender>
   <Content>大一的时候武汉有那么大</Content>
  </WeChat>
 </Dialogue>
 <Dialogue>
  <WeChat>
   <Time>2022-09-26 15:26:00</Time>
   <Sender>A</Sender>
   <Content>去找他的时间和长沙去武汉差不多</Content>
  </WeChat>
 </Dialogue>
 <Dialogue>
  <WeChat>
   <Time>2022-09-26 15:27:00</Time>
   <Sender>B</Sender>
   <Content>哈哈哈哈哈哈</Content>
  </WeChat>
 </Dialogue>
 <Dialogue>
  <WeChat>
   <Time>2022-09-26 15:27:00</Time>
   <Sender>A</Sender>
   <Content>还封校封到现在</Content>
  </WeChat>
 </Dialogue>
 <Dialogue>
  <WeChat>
   <Time>2022-09-26 15:27:00</Time>
   <Sender>A</Sender>
   <Content>妈的不早说</Content>
  </WeChat>
 </Dialogue>
 <Dialogue>
  <WeChat>
   <Time>2022-09-26 15:27:00</Time>
   <Sender>A</Sender>
   <Content>早知道在长沙了</Content>
  </WeChat>
 </Dialogue>
 <Dialogue>
  <WeChat>
   <Time>2022-09-26 15:27:00</Time>
   <Sender>A</Sender>
   <Content>狗[sensitive]</Content>
  </WeChat>
 </Dialogue>
 <Dialogue>
  <WeChat>
   <Time>2022-09-26 15:27:00</Time>
   <Sender>B</Sender>
   <Content>哈哈哈哈哈</Content>
  </WeChat>
 </Dialogue>
 <Dialogue>
  <WeChat>
   <Time>2022-09-26 15:27:00</Time>
   <Sender>A</Sender>
   <Content>唉</Content>
  </WeChat>
 </Dialogue>
 <Dialogue>
  <WeChat>
   <Time>2022-09-26 15:28:00</Time>
   <Sender>A</Sender>
   <Content>真的</Content>
  </WeChat>
 </Dialogue>
 <Dialogue>
  <WeChat>
   <Time>2022-09-26 15:28:00</Time>
   <Sender>A</Sender>
   <Content>说的对</Content>
  </WeChat>
 </Dialogue>
 <Dialogue>
  <WeChat>
   <Time>2022-09-26 15:28:00</Time>
   <Sender>A</Sender>
   <Content>以前再爱</Content>
  </WeChat>
 </Dialogue>
 <Dialogue>
  <WeChat>
   <Time>2022-09-26 15:28:00</Time>
   <Sender>A</Sender>
   <Content>分了真的变仇人了</Content>
  </WeChat>
 </Dialogue>
 <Dialogue>
  <WeChat>
   <Time>2022-09-26 15:29:00</Time>
   <Sender>B</Sender>
   <Content>哈哈哈哈哈哈</Content>
  </WeChat>
 </Dialogue>
 <Dialogue>
  <WeChat>
   <Time>2022-09-26 15:29:00</Time>
   <Sender>B</Sender>
   <Content>无法噢</Content>
  </WeChat>
 </Dialogue>
 <Dialogue>
  <WeChat>
   <Time>2022-09-26 15:30:00</Time>
   <Sender>A</Sender>
   <Content>确实 发自我的 iPhone</Content>
  </WeChat>
 </Dialogue>
</rootnode>