<?xml version="1.0" encoding="utf-8"?><rootnode>
 <Meta>
  <Source>WeChat</Source>
  <Popu>2</Popu>
  <Lang>Chinese</Lang>
  <State>D</State>
  <Gender>Unknow</Gender>
  <Note>Nothing</Note>
 </Meta>
 <Dialogue>
  <WeChat>
   <Time>2022-12-03 05:24:00</Time>
   <Sender>A</Sender>
   <Content>本来想看完世界杯睡了</Content>
  </WeChat>
 </Dialogue>
 <Dialogue>
  <WeChat>
   <Time>2022-12-03 05:24:00</Time>
   <Sender>A</Sender>
   <Content>看完就睡不着了</Content>
  </WeChat>
 </Dialogue>
 <Dialogue>
  <WeChat>
   <Time>2022-12-03 05:24:00</Time>
   <Sender>A</Sender>
   <Content>操，太黑了</Content>
  </WeChat>
 </Dialogue>
 <Dialogue>
  <WeChat>
   <Time>2022-12-03 05:24:00</Time>
   <Sender>B</Sender>
   <Content>巴西输了</Content>
  </WeChat>
 </Dialogue>
 <Dialogue>
  <WeChat>
   <Time>2022-12-03 05:24:00</Time>
   <Sender>B</Sender>
   <Content>葡萄牙输了</Content>
  </WeChat>
 </Dialogue>
 <Dialogue>
  <WeChat>
   <Time>2022-12-03 05:24:00</Time>
   <Sender>A</Sender>
   <Content>这倒不怎么</Content>
  </WeChat>
 </Dialogue>
 <Dialogue>
  <WeChat>
   <Time>2022-12-03 05:25:00</Time>
   <Sender>A</Sender>
   <Content>都是上的替补</Content>
  </WeChat>
 </Dialogue>
 <Dialogue>
  <WeChat>
   <Time>2022-12-03 05:25:00</Time>
   <Sender>A</Sender>
   <Content>尼玛，乌拉圭点球是一个不罚啊</Content>
  </WeChat>
 </Dialogue>
 <Dialogue>
  <WeChat>
   <Time>2022-12-03 05:25:00</Time>
   <Sender>B</Sender>
   <Content>没看</Content>
  </WeChat>
 </Dialogue>
 <Dialogue>
  <WeChat>
   <Time>2022-12-03 05:25:00</Time>
   <Sender>B</Sender>
   <Content>啧啧啧</Content>
  </WeChat>
 </Dialogue>
</rootnode>